<annotation>
	<folder>images</folder>
	<filename>image_2.jpg</filename>
	<path>C:\Coastal Citizen Science\CoastSnap\Python\Object Detection\strandtent\train\images\image_2.jpg</path>
	<source>
		<database>Unknown</database>
	</source>
	<size>
		<width>4032</width>
		<height>3024</height>
		<depth>3</depth>
	</size>
	<segmented>0</segmented>
	<object>
		<name>strandtent</name>
		<pose>Unspecified</pose>
		<truncated>0</truncated>
		<difficult>0</difficult>
		<bndbox>
			<xmin>3185</xmin>
			<ymin>1056</ymin>
			<xmax>3527</xmax>
			<ymax>1227</ymax>
		</bndbox>
	</object>
</annotation>
